<?xml version="1.0"?>
<!--This Document is generated by GameMaker, if you edit it by hand then you do so at your own risk!-->
<files>
  <file md5="7071C8FF42ABD18C913DAB822D616E01">Create Trail.extension.gmx</file>
  <file md5="F6691C5F8579E4C335CD3FAADBADA3D8">Create Trail\Assets\Objects\obj_arrow.object.gmx</file>
  <file md5="54A59789F39A2FEDF385FBB058979897">Create Trail\Assets\Objects\obj_ball_basic.object.gmx</file>
  <file md5="15F3F79A35AD08B1B6ADA85646230FAA">Create Trail\Assets\Objects\obj_ball_rainbow.object.gmx</file>
  <file md5="F34E418FF78606FDC339F0E6C673AACE">Create Trail\Assets\Objects\obj_ball_rainbow_rotated.object.gmx</file>
  <file md5="E7A0D0C4AD4421DFCF83B15D2EDE62F6">Create Trail\Assets\Objects\obj_block_stripe.object.gmx</file>
  <file md5="3019EC765F607D3CFEAFF4F7FD46F06C">Create Trail\Assets\Objects\obj_dna.object.gmx</file>
  <file md5="E988E44FB9D35E9D442948BCBEBF1D23">Create Trail\Assets\Objects\obj_mouse_follow.object.gmx</file>
  <file md5="A44F1F7812AC9B5FC489FFCADB4F9BF1">Create Trail\Assets\Objects\obj_ship_blue.object.gmx</file>
  <file md5="6846BA8DBA0C50B2FE2912AFB57B9B1C">Create Trail\Assets\Objects\obj_ship_gray.object.gmx</file>
  <file md5="AC0ACF8966334DCDCBA9A0F662758F70">Create Trail\Assets\Objects\obj_ship_red.object.gmx</file>
  <file md5="40D38315CA3073FD45A132342A406229">Create Trail\Assets\Objects\obj_trail.object.gmx</file>
  <file md5="9C56F4761D4D47EEC3E4CDB5D92D858A">Create Trail\Assets\Rooms\room_trail.room.gmx</file>
  <file md5="3F24D947610A06B4EC6A4FF4A859CF7F">Create Trail\Assets\Scripts\scr_create_trail.gml</file>
  <file md5="A8C0BAB6C20A1F84B763DC0BE7257C86">Create Trail\Assets\Scripts\scr_create_trail_ext.gml</file>
  <file md5="E9CF6527430EB8D491D502D16263F233">Create Trail\Assets\Scripts\scr_create_trail_full.gml</file>
  <file md5="D1DFE97F9DCC3E4CD5261FE954B45074">Create Trail\Assets\Scripts\scr_draw_trail.gml</file>
  <file md5="9E75BCF293A0197A419198CD562FF609">Create Trail\Assets\Sprites\spr_asteroid.sprite.gmx</file>
  <file md5="77F9D32982EBBA1047B51F82D90A9F8D">Create Trail\Assets\Sprites\spr_ball.sprite.gmx</file>
  <file md5="B0810A20AB811C1FE242184DAF478300">Create Trail\Assets\Sprites\spr_block.sprite.gmx</file>
  <file md5="87933485FE2BCFA9E6C3613E70075C70">Create Trail\Assets\Sprites\spr_coin.sprite.gmx</file>
  <file md5="0161CF3DC9CEB8B6EC0180C8368A5165">Create Trail\Assets\Sprites\spr_rock.sprite.gmx</file>
  <file md5="B5BB500BB6A22857D32524802047F131">Create Trail\Assets\Sprites\spr_ship.sprite.gmx</file>
  <file md5="4EBE2BA5706CC6178FE325BF2CA69A43">Create Trail\Assets\Sprites\spr_ship_gray.sprite.gmx</file>
  <file md5="516220B07A506E1C2F69FE1D01DD1723">Create Trail\Assets\Sprites\spr_ship_red.sprite.gmx</file>
  <file md5="7CF27BD115BB0E7EA508D721954CAA16">Create Trail\Assets\Sprites\spr_trail_arrow.sprite.gmx</file>
  <file md5="EA8251BF4C788C9890258352B59BDF43">Create Trail\Assets\Sprites\spr_trail_basic.sprite.gmx</file>
  <file md5="CD1D5E793E6E8E7F24891E24BD5BCC96">Create Trail\Assets\Sprites\spr_trail_dna.sprite.gmx</file>
  <file md5="A7A46060FD51EC7F2E275C6AD1051D9F">Create Trail\Assets\Sprites\spr_trail_fire.sprite.gmx</file>
  <file md5="597BBF66D95817E686CF1E24C4D7A7BD">Create Trail\Assets\Sprites\spr_trail_glow_red.sprite.gmx</file>
  <file md5="7F3867D5479379E0972AEC125BF17FF9">Create Trail\Assets\Sprites\spr_trail_neon.sprite.gmx</file>
  <file md5="11C7D0267EE3DEDF73628484580DDEDB">Create Trail\Assets\Sprites\spr_trail_rainbow.sprite.gmx</file>
  <file md5="DDDC7EAEA5C7EA130298668F9D790877">Create Trail\Assets\Sprites\spr_trail_rainbow_rotated.sprite.gmx</file>
  <file md5="F8DADCDD201D79AE16E19745CFE7F2EF">Create Trail\Assets\Sprites\spr_trail_smoke.sprite.gmx</file>
  <file md5="90F64D13E63CC97BCF192389D0F7B0A2">Create Trail\Assets\Sprites\spr_trail_stripe.sprite.gmx</file>
  <file md5="3D11DF95F83E9D13DA0EDD70895CEF23">Create Trail\Assets\Sprites\images\spr_asteroid_0.png</file>
  <file md5="C5584DDB59AF059AD331DD4ABF1F632F">Create Trail\Assets\Sprites\images\spr_ball_0.png</file>
  <file md5="B08B35F4CD6F4256F6DD00E5E2614DA3">Create Trail\Assets\Sprites\images\spr_block_0.png</file>
  <file md5="000BC881C3E91F78A9DF297F2B364BF7">Create Trail\Assets\Sprites\images\spr_coin_0.png</file>
  <file md5="E613418AC341D28392774AAD62597485">Create Trail\Assets\Sprites\images\spr_rock_0.png</file>
  <file md5="4E8C9BE1B9423B529534EF59BCA24EA7">Create Trail\Assets\Sprites\images\spr_ship_0.png</file>
  <file md5="8EFA2D813E2AC6531EF5E2AEBD782CA5">Create Trail\Assets\Sprites\images\spr_ship_gray_0.png</file>
  <file md5="5637F1D4CFE61BB7C3BFD02A6EACB5C3">Create Trail\Assets\Sprites\images\spr_ship_red_0.png</file>
  <file md5="2D35F216E40F0E25940841B9DCBE1708">Create Trail\Assets\Sprites\images\spr_trail_arrow_0.png</file>
  <file md5="CE3C598939083E7A11776579CAADE2C4">Create Trail\Assets\Sprites\images\spr_trail_basic_0.png</file>
  <file md5="21A2DC39452356C95F5270FF6B0F37EB">Create Trail\Assets\Sprites\images\spr_trail_dna_0.png</file>
  <file md5="B5D8132E92259584FA68DB784C8B4B7C">Create Trail\Assets\Sprites\images\spr_trail_fire_0.png</file>
  <file md5="B00119EEC91B6C33DAD3970967C9D35B">Create Trail\Assets\Sprites\images\spr_trail_glow_red_0.png</file>
  <file md5="CEAAD7385796011CCB5459A5C8A24526">Create Trail\Assets\Sprites\images\spr_trail_neon_0.png</file>
  <file md5="11E4C215AE8153681B41DDCBF37D3613">Create Trail\Assets\Sprites\images\spr_trail_neon_1.png</file>
  <file md5="F160B9EE3BD655DC25DDC514336EA54C">Create Trail\Assets\Sprites\images\spr_trail_rainbow_0.png</file>
  <file md5="45006B76A72E6BFF4F33F18A9FFEB1D5">Create Trail\Assets\Sprites\images\spr_trail_rainbow_rotated_0.png</file>
  <file md5="F7EF8BED69A368252CBB88E73772AE27">Create Trail\Assets\Sprites\images\spr_trail_smoke_0.png</file>
  <file md5="923CF08A7A5B019EC798D6F3F13179F3">Create Trail\Assets\Sprites\images\spr_trail_stripe_0.png</file>
  <Signature>uOJ1ZGNVCL6fuUul/9jOdVGxU7nuDHgs6f0drNmUkS9v3o76QXm9NzRYlhkJGdpfdO3rctBoSYE8YGV5b+XmdTX8QTYCUEF2Vo20yn4l4g6E3UKtFEpgvCa/nNIlsYvx6Y5nt0pEZV+YOJxK4LB0JETR6cJ3xQNOW/t4u3U/4ZX9isDqOZwkIcjDG8iEy56oo6hXGQAQUKLiCv9NcV8zPrDWad/rUpq7uaoBrcetg9MBXUiOVOP6yvxfb+Lz3LC6w7Sf3m5RgUSePe7wTeKu51UBtDeKlF4ObpkMX3d8IL+rzjWmx4ovxZYkc3GuAk2qxR3QgqBHT2i7Jjdrnj2/fA==</Signature>
  <PublicKey>2D2D2D2D2D424547494E205055424C4943204B45592D2D2D2D2D0A4D494942496A414E42676B71686B6947397730424151454641414F43415138414D49494243674B4341514541776D43313443613367722F51426D7667304171640A505A387971473544314235652B67326C6371446F327746714F744C684E596362454E6C4E535649486C527A332F367234583063776F6F764F646C33695A745A470A6C4B6C724B514A764E4950612F4741484F2F785045494579794C36735955636133694172394D416F4A7258786456554D594644536859716F526472446B4969750A586D36307871714458566C5052616F67356A7350484C69417157665A38395159476F336F475A3447546D2B4F2B4C676568554C7A6B6E6257656B6437363963500A4C74674D326F69445234507735565A646951375A3630567A677465506441326A615A6F672B42303935377A5438556C7852665551526B4D56784F553050456B760A767A75364C6E594F304B7854344F692B68702F46665737645951304C777131615750317A6B706841556649433274424E68385446563374436D4F3543454B34350A57514944415141420A2D2D2D2D2D454E44205055424C4943204B45592D2D2D2D2D0A</PublicKey>
</files>
